oc_ds_converter/__init__.py
oc_ds_converter/crossref/__init__.py
oc_ds_converter/crossref/crossref_processing.py
oc_ds_converter/crossref/extract_crossref_publishers.py
oc_ds_converter/crossref/get_not_crossref_ref.py
oc_ds_converter/datacite/__init__.py
oc_ds_converter/datacite/datacite_processing.py
oc_ds_converter/datasource/__init__.py
oc_ds_converter/datasource/config.ini
oc_ds_converter/datasource/datasource.py
oc_ds_converter/datasource/redis.py
oc_ds_converter/jalc/__init__.py
oc_ds_converter/jalc/jalc_processing.py
oc_ds_converter/lib/__init__.py
oc_ds_converter/lib/cleaner.py
oc_ds_converter/lib/csvmanager.py
oc_ds_converter/lib/file_manager.py
oc_ds_converter/lib/jsonmanager.py
oc_ds_converter/lib/master_of_regex.py
oc_ds_converter/medra/__init__.py
oc_ds_converter/medra/medra_processing.py
oc_ds_converter/metadata_manager.py
oc_ds_converter/oc_idmanager/__init__.py
oc_ds_converter/oc_idmanager/arxiv.py
oc_ds_converter/oc_idmanager/base.py
oc_ds_converter/oc_idmanager/crossref.py
oc_ds_converter/oc_idmanager/doi.py
oc_ds_converter/oc_idmanager/isbn.py
oc_ds_converter/oc_idmanager/issn.py
oc_ds_converter/oc_idmanager/jid.py
oc_ds_converter/oc_idmanager/metadata_manager.py
oc_ds_converter/oc_idmanager/oc_data_storage/__init__.py
oc_ds_converter/oc_idmanager/oc_data_storage/in_memory_manager.py
oc_ds_converter/oc_idmanager/oc_data_storage/redis_manager.py
oc_ds_converter/oc_idmanager/oc_data_storage/sqlite_manager.py
oc_ds_converter/oc_idmanager/oc_data_storage/storage_manager.py
oc_ds_converter/oc_idmanager/openalex.py
oc_ds_converter/oc_idmanager/orcid.py
oc_ds_converter/oc_idmanager/pmcid.py
oc_ds_converter/oc_idmanager/pmid.py
oc_ds_converter/oc_idmanager/ror.py
oc_ds_converter/oc_idmanager/support.py
oc_ds_converter/oc_idmanager/url.py
oc_ds_converter/oc_idmanager/viaf.py
oc_ds_converter/oc_idmanager/wikidata.py
oc_ds_converter/oc_idmanager/wikipedia.py
oc_ds_converter/openaire/__init__.py
oc_ds_converter/openaire/openaire_processing.py
oc_ds_converter-1.0.4.dist-info/METADATA
oc_ds_converter-1.0.4.dist-info/WHEEL
oc_ds_converter-1.0.4.dist-info/entry_points.txt
oc_ds_converter-1.0.4.dist-info/RECORD
