Metadata-Version: 2.1
Name: oc-ds-converter
Version: 1.0.4
Summary: A library for converting metadata provided by various data sources, e.g. Crossref, DataCite, JaLC, and mEDRA, into the format used by OpenCitations Meta.
License: ISC
Author: arcangelo7
Author-email: arcangelomas@gmail.com
Requires-Python: >=3.9,<3.14
Classifier: License :: OSI Approved
Classifier: Programming Language :: Python :: 3
Classifier: Programming Language :: Python :: 3.9
Classifier: Programming Language :: Python :: 3.10
Classifier: Programming Language :: Python :: 3.11
Classifier: Programming Language :: Python :: 3.12
Classifier: Programming Language :: Python :: 3.13
Requires-Dist: PyYAML (>=6.0,<7.0)
Requires-Dist: beautifulsoup4 (>=4.12.1,<5.0.0)
Requires-Dist: fakeredis (>=2.14.0,<3.0.0)
Requires-Dist: filelock (>=3.12.2,<4.0.0)
Requires-Dist: lxml (>=4.9.2,<6.0.0)
Requires-Dist: ndjson (>=0.3.1,<0.4.0)
Requires-Dist: packaging (>=23.1,<24.0)
Requires-Dist: pandas (>=2.2.3,<3.0.0)
Requires-Dist: pebble (>=5.0.3,<6.0.0)
Requires-Dist: poetry (>=1.5.1,<2.0.0)
Requires-Dist: python-dateutil (>=2.8.2,<3.0.0)
Requires-Dist: redis (>=4.5.5,<5.0.0)
Requires-Dist: requests (>=2.28.2,<3.0.0)
Requires-Dist: self (>=2020.12.3,<2021.0.0)
Requires-Dist: six (>=1.16.0,<2.0.0)
Requires-Dist: tqdm (>=4.65.0,<5.0.0)
Requires-Dist: update (>=0.0.1,<0.0.2)
Requires-Dist: validators (>=0.20.0,<0.21.0)
Requires-Dist: xmltodict (>=0.13.0,<0.14.0)
Requires-Dist: zstandard (>=0.21.0,<0.22.0)
